[
  {
    "task_id": "t_001",
    "assignee_ids": [
      "u_001",
      "u_002"
    ],
    "location_id": "loc_001",
    "date": "2026-04-06",
    "start_time": "09:40",
    "end_time": "10:40",
    "is_locked": false,
    "block_status": "pending",
    "memo": "",
    "identifier_ids": [
      "TC-001",
      "TC-003"
    ],
    "title": "",
    "is_simple": false,
    "overflow_minutes": 0,
    "id": "sb_e7db8f95"
  },
  {
    "task_id": "t_001",
    "assignee_ids": [
      "u_001",
      "u_002"
    ],
    "location_id": "loc_002",
    "date": "2026-04-06",
    "start_time": "09:50",
    "end_time": "10:33",
    "is_locked": false,
    "block_status": "pending",
    "memo": "",
    "identifier_ids": [
      "TC-002"
    ],
    "title": "",
    "is_simple": false,
    "overflow_minutes": 0,
    "id": "sb_be15040f"
  },
  {
    "task_id": "t_009",
    "assignee_ids": [
      "u_001",
      "u_002"
    ],
    "location_id": "loc_003",
    "date": "2026-04-06",
    "start_time": "09:40",
    "end_time": "10:44",
    "is_locked": false,
    "block_status": "pending",
    "memo": "",
    "identifier_ids": null,
    "title": "",
    "is_simple": false,
    "overflow_minutes": 0,
    "id": "sb_17e87bc8"
  },
  {
    "task_id": "t_002",
    "assignee_ids": [
      "u_002",
      "u_003"
    ],
    "location_id": "loc_001",
    "date": "2026-04-08",
    "start_time": "08:50",
    "end_time": "09:50",
    "is_locked": false,
    "block_status": "pending",
    "memo": "",
    "identifier_ids": null,
    "title": "",
    "is_simple": false,
    "overflow_minutes": 0,
    "id": "sb_aab9a94d"
  },
  {
    "task_id": "t_003",
    "assignee_ids": [
      "u_003",
      "u_004"
    ],
    "location_id": "loc_002",
    "date": "2026-04-07",
    "start_time": "08:30",
    "end_time": "10:44",
    "is_locked": false,
    "block_status": "pending",
    "memo": "",
    "identifier_ids": null,
    "title": "",
    "is_simple": false,
    "overflow_minutes": 0,
    "id": "sb_7db79de1"
  },
  {
    "task_id": "t_006",
    "assignee_ids": [
      "u_001",
      "u_003"
    ],
    "location_id": "loc_001",
    "date": "2026-04-07",
    "start_time": "08:40",
    "end_time": "09:40",
    "is_locked": false,
    "block_status": "pending",
    "memo": "",
    "identifier_ids": null,
    "title": "",
    "is_simple": false,
    "overflow_minutes": 0,
    "id": "sb_5adfa997"
  },
  {
    "task_id": "t_005",
    "assignee_ids": [
      "u_002"
    ],
    "location_id": "loc_003",
    "date": "2026-04-07",
    "start_time": "10:20",
    "end_time": "11:40",
    "is_locked": false,
    "block_status": "pending",
    "memo": "",
    "identifier_ids": null,
    "title": "",
    "is_simple": false,
    "overflow_minutes": 0,
    "id": "sb_9dc02d25"
  }
]